[
  {
    "name": "acw_tc",
    "value": "ac11000117417010192785988e00432763ad81693e9a9cb4555f9e4388892b",
    "domain": "passport.zhihuishu.com",
    "port": null,
    "path": "/",
    "expires": 1741702820,
    "secure": false,
    "rest": {
      "HttpOnly": null
    },
    "version": 0,
    "comment": null,
    "comment_url": null,
    "rfc2109": false,
    "discard": false
  },
  {
    "name": "INGRESSCOOKIE",
    "value": "1741701020.291.35964.612421",
    "domain": "passport.zhihuishu.com",
    "port": null,
    "path": "/",
    "expires": 1741873820,
    "secure": false,
    "rest": {
      "HttpOnly": null
    },
    "version": 0,
    "comment": null,
    "comment_url": null,
    "rfc2109": false,
    "discard": false
  },
  {
    "name": "SERVERID",
    "value": "472b148b148a839eba1c5c1a8657e3a7|1741701062|1741701019",
    "domain": "passport.zhihuishu.com",
    "port": null,
    "path": "/",
    "expires": null,
    "secure": false,
    "rest": {},
    "version": 0,
    "comment": null,
    "comment_url": null,
    "rfc2109": false,
    "discard": true
  },
  {
    "name": "CASTGC",
    "value": "TGT-3769099-KSQ5eXvCMCjWo350wHhyQXYquTVRn6YLhb5eQoIwFvm05zf3OM-passport.zhihuishu.com",
    "domain": ".zhihuishu.com",
    "port": null,
    "path": "/",
    "expires": null,
    "secure": false,
    "rest": {},
    "version": 0,
    "comment": null,
    "comment_url": null,
    "rfc2109": false,
    "discard": true
  },
  {
    "name": "CASLOGC",
    "value": "%7B%22realName%22%3A%22%E7%8E%8B%E7%85%9C%E8%8A%9D%22%2C%22myuniRole%22%3A0%2C%22myinstRole%22%3A0%2C%22userId%22%3A868446037%2C%22headPic%22%3A%22https%3A%2F%2Fimage.zhihuishu.com%2Fzhs%2Fablecommons%2Fdemo%2F201804%2F5e314c660d31448d94fc201d434ca736_s3.jpg%22%2C%22uuid%22%3A%22VvROmryr%22%2C%22mycuRole%22%3A0%2C%22username%22%3A%22263be9aff37e46e48be7c0fe4fa1d1b3%22%7D",
    "domain": ".zhihuishu.com",
    "port": null,
    "path": "/",
    "expires": null,
    "secure": false,
    "rest": {},
    "version": 0,
    "comment": null,
    "comment_url": null,
    "rfc2109": false,
    "discard": true
  },
  {
    "name": "jt-cas",
    "value": "eyJraWQiOiJFRjRGMjJDMC01Q0IwLTQzNDgtOTY3Qi0wMjY0OTVFN0VGQzgiLCJhbGciOiJFUzI1NiJ9.eyJpc3MiOiJjb20uemhpaHVpc2h1IiwiYXVkIjoiQ0FTIiwic3ViIjoi546L54Wc6IqdIiwiaWF0IjoxNzQxNzAxMDYyLCJleHAiOjE3NDE3ODc0NjIsImp0aSI6IjYwNzI2NDE0LTBiYzItNDE3Yi05MTQyLTZiMGQzNGQ4OThjNSIsInVpZCI6ODY4NDQ2MDM3fQ.mYFdpryguMdEbldEwEosRb8zyQdrxaC6QjUrtTE8mXFp1RVEXfDWP5FfZ3X-PgRApf9JuuP9KwtHorVnUaiGJw",
    "domain": ".zhihuishu.com",
    "port": null,
    "path": "/",
    "expires": null,
    "secure": false,
    "rest": {},
    "version": 0,
    "comment": null,
    "comment_url": null,
    "rfc2109": false,
    "discard": true
  },
  {
    "name": "acw_tc",
    "value": "1a0c595b17417010630186903e00343ee42b89811a1e7b6c03f399f6a5e1b8",
    "domain": "onlineservice-api.zhihuishu.com",
    "port": null,
    "path": "/",
    "expires": 1741702863,
    "secure": false,
    "rest": {
      "HttpOnly": null
    },
    "version": 0,
    "comment": null,
    "comment_url": null,
    "rfc2109": false,
    "discard": false
  },
  {
    "name": "SERVERID",
    "value": "fe82cac8f8e600c79e0f3988dddd82bc|1741701063|1741701063",
    "domain": "onlineservice-api.zhihuishu.com",
    "port": null,
    "path": "/",
    "expires": null,
    "secure": false,
    "rest": {},
    "version": 0,
    "comment": null,
    "comment_url": null,
    "rfc2109": false,
    "discard": true
  },
  {
    "name": "SERVERID",
    "value": "58a6d0bed134adfd5bca4c165678e873|1741701063|1741701063",
    "domain": "www.zhihuishu.com",
    "port": null,
    "path": "/",
    "expires": null,
    "secure": false,
    "rest": {},
    "version": 0,
    "comment": null,
    "comment_url": null,
    "rfc2109": false,
    "discard": true
  },
  {
    "name": "exitRecod_VvROmryr",
    "value": "2",
    "domain": "",
    "port": null,
    "path": "/",
    "expires": null,
    "secure": false,
    "rest": {
      "HttpOnly": null
    },
    "version": 0,
    "comment": null,
    "comment_url": null,
    "rfc2109": false,
    "discard": true
  }
]